Radzymlib/CalcFunctions.py
Radzymlib/TkinkerExtension.py
Radzymlib/__init__.py
Radzymlis-0.0.1.dist-info/METADATA
Radzymlis-0.0.1.dist-info/WHEEL
Radzymlis-0.0.1.dist-info/top_level.txt
Radzymlis-0.0.1.dist-info/RECORD
