Metadata-Version: 2.1
Name: Radzymlis
Version: 0.0.1
Summary: Useful methods
Author: Radzym (Radim Slovák)
Author-email: <slovak.radim@seznam.cz>
Keywords: python,data analysis,physics
Classifier: Development Status :: 1 - Planning
Classifier: Intended Audience :: Developers
Classifier: Programming Language :: Python :: 3
Classifier: Operating System :: Unix
Classifier: Operating System :: MacOS :: MacOS X
Classifier: Operating System :: Microsoft :: Windows
